paramSeeker/__init__.py
paramSeeker/example.py
paramSeeker/seeker.py
paramSeeker-0.3.3.dist-info/DESCRIPTION.rst
paramSeeker-0.3.3.dist-info/METADATA
paramSeeker-0.3.3.dist-info/RECORD
paramSeeker-0.3.3.dist-info/WHEEL
paramSeeker-0.3.3.dist-info/entry_points.txt
paramSeeker-0.3.3.dist-info/metadata.json
paramSeeker-0.3.3.dist-info/top_level.txt
