Metadata-Version: 2.0
Name: paramSeeker
Version: 0.3.3
Summary: Terminal parameter retrive then 执行以及参数转发，开发实体内容
Home-page: https://github.com/hellflame/paramSeeker
Author: hellflame
Author-email: hellflamedly@gmail.com
License: Apache License
Keywords: param,parameter,terminal handler
Platform: any
Classifier: Development Status :: 5 - Production/Stable
Classifier: Intended Audience :: Developers
Classifier: License :: OSI Approved :: Apache Software License
Classifier: Topic :: Software Development :: Libraries
Classifier: Topic :: Software Development :: Libraries :: Python Modules
Classifier: Programming Language :: Python
Classifier: Programming Language :: Python :: 2.7
Classifier: Programming Language :: Python :: 3.4
Classifier: Operating System :: OS Independent
